nornir_f5/__init__.py
nornir_f5/plugins/__init__.py
nornir_f5/plugins/connections/__init__.py
nornir_f5/plugins/connections/f5.py
nornir_f5/plugins/tasks/__init__.py
nornir_f5/plugins/tasks/atc.py
nornir_f5/plugins/tasks/bigip/__init__.py
nornir_f5/plugins/tasks/bigip/cm/__init__.py
nornir_f5/plugins/tasks/bigip/cm/config_sync.py
nornir_f5/plugins/tasks/bigip/cm/failover_status.py
nornir_f5/plugins/tasks/bigip/cm/sync_status.py
nornir_f5/plugins/tasks/bigip/shared/__init__.py
nornir_f5/plugins/tasks/bigip/shared/file_transfer/__init__.py
nornir_f5/plugins/tasks/bigip/shared/file_transfer/uploads.py
nornir_f5/plugins/tasks/bigip/shared/iapp/__init__.py
nornir_f5/plugins/tasks/bigip/shared/iapp/package_management_tasks.py
nornir_f5/plugins/tasks/bigip/sys/__init__.py
nornir_f5/plugins/tasks/bigip/sys/version.py
nornir_f5/plugins/tasks/bigip/util/__init__.py
nornir_f5/plugins/tasks/bigip/util/unix_ls.py
nornir_f5/plugins/tasks/bigip/util/unix_rm.py
nornir_f5-0.7.0.dist-info/LICENSE
nornir_f5-0.7.0.dist-info/METADATA
nornir_f5-0.7.0.dist-info/WHEEL
nornir_f5-0.7.0.dist-info/entry_points.txt
nornir_f5-0.7.0.dist-info/RECORD
