Metadata-Version: 2.1
Name: nornir-f5
Version: 0.7.0
Summary: F5 plugins for Nornir
Home-page: https://github.com/erjac77/nornir_f5
License: Apache-2.0
Keywords: nornir,f5,bigip,automation,as3
Author: Eric Jacob
Author-email: erjac77@gmail.com
Requires-Python: >=3.7.2,<4.0.0
Classifier: License :: OSI Approved :: Apache Software License
Classifier: Programming Language :: Python :: 3
Classifier: Programming Language :: Python :: 3.8
Classifier: Programming Language :: Python :: 3.9
Classifier: Programming Language :: Python :: 3.10
Classifier: Programming Language :: Python :: 3.11
Classifier: Programming Language :: Python :: 3
Classifier: Programming Language :: Python :: 3.7
Classifier: Programming Language :: Python :: 3.8
Classifier: Programming Language :: Python :: 3.9
Classifier: Topic :: System :: Networking
Requires-Dist: nornir (>=3.3.0,<4.0.0)
Requires-Dist: packaging (>=23.0,<24.0)
Requires-Dist: requests (>=2.28.2,<3.0.0)
Requires-Dist: requests-toolbelt (>=0.10.1,<0.11.0)
Requires-Dist: urllib3 (>=1.26.14,<2.0.0)
Project-URL: Documentation, https://github.com/erjac77/nornir_f5
Project-URL: Issues, https://github.com/erjac77/nornir_f5/issues
Project-URL: Pull Requests, https://github.com/erjac77/nornir_f5/pulls
Project-URL: Repository, https://github.com/erjac77/nornir_f5
Project-URL: Releases, https://github.com/erjac77/nornir_f5/releases
